mimodulito
