Metadata-Version: 2.1
Name: mimodulito
Version: 0.3
Summary: Calculate modulus
Home-page: https://pypi.org/project/mimodulito
Author: Daniel Niño Villegas
Author-email: daniel.ninov@udea.edu.co
License: MIT
Keywords: Modulo
Platform: UNKNOWN
Classifier: Programming Language :: Python :: 3
Classifier: License :: OSI Approved :: MIT License
Classifier: Operating System :: OS Independent
License-File: LICENSE
